word_tower/__init__.py
word_tower/main.py
word_tower/app/__init__.py
word_tower/app/main.py
word_tower/app/assets/dicts/com_acento.txt
word_tower/app/assets/dicts/sem_acento.txt
word_tower/app/classes/__init__.py
word_tower/app/classes/player.py
word_tower/app/utils/__init__.py
word_tower/app/utils/dictionary.py
word_tower/app/ws/__init__.py
word_tower/app/ws/game_manager.py
word_tower/static/android-chrome-192x192.png
word_tower/static/android-chrome-512x512.png
word_tower/static/apple-touch-icon.png
word_tower/static/favicon-16x16.png
word_tower/static/favicon-32x32.png
word_tower/static/favicon.ico
word_tower/static/index.html
word_tower/static/site.webmanifest
word_tower/static/assets/index-Cr3lPTT6.css
word_tower/static/assets/index-DGcWXRJB.js
word_tower/static/assets/logo-Cf0zZ-Pv.png
word_tower/static/assets/start_screen_bg-BX-FcyKd.png
word_tower/static/assets/tomo_bossa_black-CI24Ev11.woff
word_tower_game-1.0.3.dist-info/licenses/LICENSE
word_tower_game-1.0.3.dist-info/METADATA
word_tower_game-1.0.3.dist-info/WHEEL
word_tower_game-1.0.3.dist-info/entry_points.txt
word_tower_game-1.0.3.dist-info/top_level.txt
word_tower_game-1.0.3.dist-info/RECORD
