Metadata-Version: 2.4
Name: word-tower-game
Version: 1.0.3
Summary: A multiplayer word game with real-time gameplay via WebSocket
Author-email: KJSS3012 <contato@wordtower.game>
License-Expression: MIT
Project-URL: Homepage, https://github.com/KJSS3012/word-tower
Project-URL: Repository, https://github.com/KJSS3012/word-tower
Project-URL: Issues, https://github.com/KJSS3012/word-tower/issues
Project-URL: Documentation, https://github.com/KJSS3012/word-tower#readme
Keywords: game,multiplayer,websocket,words,real-time
Classifier: Development Status :: 4 - Beta
Classifier: Intended Audience :: End Users/Desktop
Classifier: Programming Language :: Python :: 3
Classifier: Programming Language :: Python :: 3.8
Classifier: Programming Language :: Python :: 3.9
Classifier: Programming Language :: Python :: 3.10
Classifier: Programming Language :: Python :: 3.11
Classifier: Programming Language :: Python :: 3.12
Classifier: Topic :: Games/Entertainment :: Puzzle Games
Requires-Python: >=3.8
License-File: LICENSE
Requires-Dist: fastapi>=0.104.1
Requires-Dist: uvicorn[standard]>=0.24.0
Requires-Dist: python-socketio>=5.10.0
Requires-Dist: python-multipart>=0.0.6
Requires-Dist: jinja2>=3.1.2
Requires-Dist: aiofiles>=23.2.1
Dynamic: license-file
